README.md
setup.py
scalaccf/ScalaCCF.py
scalaccf/__init__.py
scalaccf/__main__.py
scalaccf/ccf.py
scalaccf/formatter.py
scalaccf/lexer.py
scalaccf/rename_dirs.py
scalaccf/utility.py
scalaccf.egg-info/PKG-INFO
scalaccf.egg-info/SOURCES.txt
scalaccf.egg-info/dependency_links.txt
scalaccf.egg-info/entry_points.txt
scalaccf.egg-info/top_level.txt