Metadata-Version: 2.1
Name: scalaccf
Version: 0.1.28
Summary: ScalaCCF - utility to fix style and documentation comments in Scala files
Home-page: https://github.com/JustTaya/MetaProg/tree/lab-2/Lab2
Author: Taisiia Velychko
Author-email: justataya@gmail.com
License: UNKNOWN
Platform: UNKNOWN
